inmanta_plugins/std/__init__.py
inmanta_plugins/std/resources.py
inmanta_plugins/std/setup.cfg
inmanta_plugins/std/types.py
inmanta_plugins/std/model/_init.cf
inmanta_plugins/std/model/testing.cf
inmanta_plugins/std/templates/host_uri.j2
inmanta_module_std-8.7.0.dist-info/METADATA
inmanta_module_std-8.7.0.dist-info/WHEEL
inmanta_module_std-8.7.0.dist-info/top_level.txt
inmanta_module_std-8.7.0.dist-info/RECORD
