Metadata-Version: 2.4
Name: inmanta-module-std
Version: 8.7.0
License: Apache 2.0
Requires-Python: >=3.12
Requires-Dist: Jinja2<4,>=3.1
Requires-Dist: email_validator<3,>=1.3
Requires-Dist: pydantic<3,>=1.10
Requires-Dist: inmanta-core>=8.7.0.dev
